tm_sl/__init__.py
tm_sl/adapters/__init__.py
tm_sl/cli/__init__.py
tm_sl/cli/group.py
tm_sl/cli/main.py
tm_sl/cli/migrate.py
tm_sl/cli/project.py
tm_sl/cli/snaplex.py
tm_sl/cli/task.py
tm_sl/cli/tenant.py
tm_sl/com/__init__.py
tm_sl/com/json_util.py
tm_sl/com/printing.py
tm_sl/com/traceback.py
tm_sl/sl/__init__.py
tm_sl/sl/groups.py
tm_sl/sl/manager.py
tm_sl/sl/migration.py
tm_sl/sl/projects.py
tm_sl/sl/snaplexes.py
tm_sl/sl/tasks.py
tm_sl/sl/tenants.py
tm_sl/sl/users.py
tm_sl-0.2.5.dist-info/METADATA
tm_sl-0.2.5.dist-info/WHEEL
tm_sl-0.2.5.dist-info/entry_points.txt
tm_sl-0.2.5.dist-info/RECORD
