Metadata-Version: 2.1
Name: tm-sl
Version: 0.2.5
Summary: A Library for interacting with the snaplogic API
License: proprietary - private
Author: Gene Myslinsky
Author-email: Gene.Myslinsky@insightsoftware.com
Requires-Python: >=3.8,<4.0
Classifier: License :: Other/Proprietary License
Classifier: Programming Language :: Python :: 3
Classifier: Programming Language :: Python :: 3.8
Classifier: Programming Language :: Python :: 3.9
Classifier: Programming Language :: Python :: 3.10
Classifier: Programming Language :: Python :: 3.11
Requires-Dist: click (>=8.1.7,<9.0.0)
Requires-Dist: python-dotenv (>=1.0.0,<2.0.0)
Requires-Dist: requests (>=2.31.0,<3.0.0)
Requires-Dist: rich (>=13.6.0,<14.0.0)
Requires-Dist: tenacity (>=8.2.3,<9.0.0)
